{
  "checkbox": {
    "height": {
      "default": {
        "value": "{semantic.sizing.inputs.xs}",
        "type": "sizing"
      }
    },
    "width": {
      "default": {
        "value": "{semantic.sizing.inputs.xs}",
        "type": "sizing"
      }
    },
    "icon-size": {
      "value": "14",
      "type": "sizing"
    },
    "unchecked": {
      "default": {
        "icon-color": {
          "value": "{semantic.color.inputs.icon-color.default}",
          "type": "color"
        }
      },
      "hover": {
        "icon-color": {
          "value": "{semantic.color.inputs.icon-color.hover}",
          "type": "color"
        }
      },
      "disabled": {
        "icon-color": {
          "value": "{semantic.color.inputs.icon-color.disabled}",
          "type": "color"
        }
      },
      "error": {
        "icon-color": {
          "value": "{semantic.color.inputs.icon-color.danger}",
          "type": "color"
        }
      }
    },
    "checked": {
      "default": {
        "icon-color": {
          "value": "{semantic.color.inputs.icon-color.selected}",
          "type": "color"
        }
      },
      "hover": {
        "icon-color": {
          "value": "{semantic.color.inputs.icon-color.hover}",
          "type": "color"
        }
      },
      "disabled": {
        "icon-color": {
          "value": "{semantic.color.inputs.icon-color.disabled}",
          "type": "color"
        }
      }
    },
    "itemSpacing": {
      "value": "{semantic.spacing.inputs.itemSpacing.sm}",
      "type": "spacing"
    }
  }
}